main/__init__.py
main/automl_processor.py
main/common.py
main/run.py
prepup_linux-0.2.3.dist-info/LICENSE
prepup_linux-0.2.3.dist-info/METADATA
prepup_linux-0.2.3.dist-info/WHEEL
prepup_linux-0.2.3.dist-info/entry_points.txt
prepup_linux-0.2.3.dist-info/top_level.txt
prepup_linux-0.2.3.dist-info/RECORD
