Metadata-Version: 2.1
Name: prepup-linux
Version: 0.2.3
Summary: Prepup is a free, open-source package for data preprocessing in terminal
Home-page: https://github.com/sudhanshumukherjeexx/prepup-linux
Author: Sudhanshu Mukherjee
Author-email: sudhanshumukherjeexx@gmail.com
Project-URL: Bug Reports, https://github.com/sudhanshumukherjeexx/prepup-linux/issues
Project-URL: Source, https://github.com/sudhanshumukherjeexx/prepup-linux
Keywords: data-preprocessing machine-learning data-science
Classifier: Development Status :: 4 - Beta
Classifier: Intended Audience :: Developers
Classifier: Intended Audience :: Science/Research
Classifier: License :: OSI Approved :: MIT License
Classifier: Operating System :: OS Independent
Classifier: Programming Language :: Python :: 3
Classifier: Programming Language :: Python :: 3.7
Classifier: Programming Language :: Python :: 3.8
Classifier: Programming Language :: Python :: 3.9
Classifier: Programming Language :: Python :: 3.10
Classifier: Topic :: Scientific/Engineering :: Information Analysis
Classifier: Topic :: Software Development :: Libraries :: Python Modules
Requires-Python: >=3.7
License-File: LICENSE
Requires-Dist: blessed==1.19.1
Requires-Dist: imbalanced-learn==0.10.1
Requires-Dist: imblearn==0.0
Requires-Dist: joblib==1.2.0
Requires-Dist: matplotlib==3.10.1
Requires-Dist: numpy==2.2.3
Requires-Dist: pandas==2.2.3
Requires-Dist: plotext==5.2.8
Requires-Dist: pydantic==2.10.6
Requires-Dist: pyfiglet==0.8.post1
Requires-Dist: pytest==7.3.1
Requires-Dist: scikit-learn==1.6.1
Requires-Dist: scipy==1.15.2
Requires-Dist: termcolor==2.3.0
Requires-Dist: pyarrow==19.0.1
Requires-Dist: seaborn==0.11.2
Requires-Dist: tqdm==4.66.1
Requires-Dist: lightgbm==4.6.0
Requires-Dist: xgboost==2.1.4
Requires-Dist: nbformat==5.10.0
Requires-Dist: setuptools==76.1.0
Provides-Extra: dev
Requires-Dist: pytest; extra == "dev"
Requires-Dist: twine; extra == "dev"
Requires-Dist: wheel; extra == "dev"
